fw_curate_bids/BIDSCuration.py
fw_curate_bids/__init__.py
fw_curate_bids/get_bids.py
fw_curate_bids/main.py
fw_curate_bids/parser.py
fw_curate_bids/save_bids_curation.py
fw_curate_bids/save_config.py
fw_curate_bids-2.2.14.dist-info/LICENSE
fw_curate_bids-2.2.14.dist-info/METADATA
fw_curate_bids-2.2.14.dist-info/WHEEL
fw_curate_bids-2.2.14.dist-info/RECORD
