Metadata-Version: 2.1
Name: fw-curate-bids
Version: 2.2.14
Summary: Use this gear to initialize BIDS filenames and attributes on all files within a given project.
Home-page: https://gitlab.com/flywheel-io/flywheel-apps/templates/skeleton
License: MIT
Keywords: Flywheel,Gears
Author: Flywheel
Author-email: support@flywheel.io
Requires-Python: >=3.11,<4.0
Classifier: License :: OSI Approved :: MIT License
Classifier: Programming Language :: Python :: 3
Classifier: Programming Language :: Python :: 3.11
Classifier: Programming Language :: Python :: 3.12
Classifier: Topic :: Scientific/Engineering
Requires-Dist: flywheel-bids (>=1.2.28,<2.0.0)
Requires-Dist: flywheel-sdk (>=17.0,<18.0)
Requires-Dist: numpy (<2.0.0)
Requires-Dist: pandas (>=1.3.3,<2.0.0)
Project-URL: Repository, https://gitlab.com/flywheel-io/flywheel-apps/templates/skeleton
